MatFold/__init__.py
MatFold/_version.py
MatFold/main.py
MatFold/utils.py
matfold-1.3.3.dist-info/licenses/LICENSE.md
matfold-1.3.3.dist-info/METADATA
matfold-1.3.3.dist-info/WHEEL
matfold-1.3.3.dist-info/top_level.txt
matfold-1.3.3.dist-info/RECORD
