Metadata-Version: 2.4
Name: MatFold
Version: 1.3.3
Summary: Package for systematic insights into materials discovery models’ performance through standardized chemical cross-validation protocols
Author-email: Peter Schindler <p.schindler@northeastern.edu>, "Matthew D. Witman" <mwitman@sandia.gov>
Maintainer-email: Peter Schindler <p.schindler@northeastern.edu>
License: MIT License
Project-URL: Repository, https://github.com/d2r2group/MatFold
Keywords: machine learning,materials science,cross-validation,generalization error
Classifier: Programming Language :: Python
Classifier: Programming Language :: Python :: 3.10
Classifier: Programming Language :: Python :: 3.11
Classifier: Programming Language :: Python :: 3.12
Classifier: Intended Audience :: Science/Research
Classifier: Topic :: Scientific/Engineering
Classifier: Operating System :: Microsoft :: Windows
Classifier: Operating System :: Unix
Classifier: Operating System :: MacOS
Classifier: License :: OSI Approved :: MIT License
Requires-Python: >=3.10
License-File: LICENSE.md
Requires-Dist: numpy
Requires-Dist: pandas
Requires-Dist: pymatgen>=2024
Dynamic: license-file
